photo_sorter/__init__.py
photo_sorter/__main__.py
photo_sorter/sorting.py
photo_org-0.1.0.dist-info/LICENSE.md
photo_org-0.1.0.dist-info/METADATA
photo_org-0.1.0.dist-info/WHEEL
photo_org-0.1.0.dist-info/entry_points.txt
photo_org-0.1.0.dist-info/top_level.txt
photo_org-0.1.0.dist-info/RECORD
