Metadata-Version: 2.1
Name: photo-org
Version: 0.1.0
Summary: A tool that sorts photos in a dated folder structure.
Home-page: https://github.com/dwardu89/photo_sorter
Author: Edward Vella
Author-email: hello@dwardu.com
License: UNKNOWN
Platform: UNKNOWN
Classifier: License :: OSI Approved :: GNU General Public License v3 (GPLv3)
Requires-Dist: exifread
Requires-Dist: Pillow
Requires-Dist: colorama
